hardware_metrics/__init__.py
hardware_metrics/main.py
hardware_metrics-0.0.3.dist-info/LICENSE
hardware_metrics-0.0.3.dist-info/METADATA
hardware_metrics-0.0.3.dist-info/WHEEL
hardware_metrics-0.0.3.dist-info/top_level.txt
hardware_metrics-0.0.3.dist-info/RECORD
