Metadata-Version: 2.1
Name: hardware_metrics
Version: 0.0.3
Summary: Decorador que proporciona estadisticas del hardware
Author-email: Pablo Baggetto <pbaggetto@iti.com>, Nikita Teslenko Grygoryev <nteslenko@iti.com>
Classifier: Programming Language :: Python :: 3
Requires-Python: >=3.10
License-File: LICENSE
Requires-Dist: contourpy
Requires-Dist: cycler
Requires-Dist: fonttools
Requires-Dist: kiwisolver
Requires-Dist: matplotlib
Requires-Dist: numpy
Requires-Dist: nvidia-ml-py3
Requires-Dist: packaging
Requires-Dist: pandas
Requires-Dist: Pillow
Requires-Dist: psutil
Requires-Dist: pyparsing
Requires-Dist: python-dateutil
Requires-Dist: pytz
Requires-Dist: seaborn
Requires-Dist: six
Requires-Dist: tzdata
